data_pipeline/__init__.py
data_pipeline/application.py
data_pipeline/config.py
data_pipeline/content/config/__init__.py
data_pipeline/content/config/csv.yml
data_pipeline/content/config/excel.yml
data_pipeline/data/census/__init__.py
data_pipeline/data/census/csv/__init__.py
data_pipeline/data/census/geojson/__init__.py
data_pipeline/data/census/shp/__init__.py
data_pipeline/data/dataset/__init__.py
data_pipeline/data/score/csv/__init__.py
data_pipeline/data/score/downloadable/__init__.py
data_pipeline/data/score/geojson/__init__.py
data_pipeline/data/score/shapefile/__init__.py
data_pipeline/data/score/tiles/__init__.py
data_pipeline/etl/__init__.py
data_pipeline/etl/base.py
data_pipeline/etl/constants.py
data_pipeline/etl/runner.py
data_pipeline/etl/score/__init__.py
data_pipeline/etl/score/constants.py
data_pipeline/etl/score/etl_score.py
data_pipeline/etl/score/etl_score_geo.py
data_pipeline/etl/score/etl_score_post.py
data_pipeline/etl/score/etl_utils.py
data_pipeline/etl/score/tests/__init__.py
data_pipeline/etl/score/tests/conftest.py
data_pipeline/etl/score/tests/sample_data/__init__.py
data_pipeline/etl/score/tests/sample_data/county_data_initial.csv
data_pipeline/etl/score/tests/sample_data/score_data_initial.csv
data_pipeline/etl/score/tests/sample_data/state_data_initial.csv
data_pipeline/etl/score/tests/snapshots/downloadable_data_expected.pkl
data_pipeline/etl/score/tests/snapshots/score_data_expected.pkl
data_pipeline/etl/score/tests/snapshots/score_transformed_expected.pkl
data_pipeline/etl/score/tests/snapshots/tile_data_expected.pkl
data_pipeline/etl/score/tests/test_etl_utils.py
data_pipeline/etl/score/tests/test_score_post.py
data_pipeline/etl/sources/__init__.py
data_pipeline/etl/sources/calenviroscreen/README.md
data_pipeline/etl/sources/calenviroscreen/__init__.py
data_pipeline/etl/sources/calenviroscreen/etl.py
data_pipeline/etl/sources/cdc_life_expectancy/README.md
data_pipeline/etl/sources/cdc_life_expectancy/__init__.py
justice40_data_pipeline-0.1.0.dist-info/WHEEL
justice40_data_pipeline-0.1.0.dist-info/METADATA
justice40_data_pipeline-0.1.0.dist-info/RECORD
