Metadata-Version: 2.1
Name: justice40-data-pipeline
Version: 0.1.0
Summary: ETL, Score and Map Generation of Justice 40 Tool
Home-page: https://github.com/usds/justice40-tool/tree/main/data/data-pipeline
License: MIT
Keywords: justice40,environmental_justice,python,etl
Author: Justice40 Engineering
Author-email: j40-engineering@lists.usds.gov
Requires-Python: >=3.8,<4.0
Classifier: License :: OSI Approved :: MIT License
Classifier: Programming Language :: Python :: 3
Classifier: Programming Language :: Python :: 3.10
Classifier: Programming Language :: Python :: 3.8
Classifier: Programming Language :: Python :: 3.9
Requires-Dist: CensusData (>=1.13,<2.0)
Requires-Dist: PyYAML (>=6.0,<7.0)
Requires-Dist: click (>=8.0.1,<9.0.0)
Requires-Dist: dynaconf (>=3.1.4,<4.0.0)
Requires-Dist: geopandas (>=0.9.0,<0.10.0)
Requires-Dist: ipdb (>=0.13.9,<0.14.0)
Requires-Dist: ipython (>=7.31.1,<8.0.0)
Requires-Dist: jupyter (>=1.0.0,<2.0.0)
Requires-Dist: jupyter-contrib-nbextensions (>=0.5.1,<0.6.0)
Requires-Dist: matplotlib (>=3.4.2,<4.0.0)
Requires-Dist: numpy (>=1.22.1,<2.0.0)
Requires-Dist: pandas (>=1.2.5,<2.0.0)
Requires-Dist: pillow (==9.0.1)
Requires-Dist: pylint (>=2.11.1,<3.0.0)
Requires-Dist: pypandoc (>=1.6.3,<2.0.0)
Requires-Dist: requests (>=2.25.1,<3.0.0)
Requires-Dist: tqdm (==4.62.0)
Requires-Dist: types-requests (>=2.25.0,<3.0.0)
Requires-Dist: us (>=2.0.2,<3.0.0)
Requires-Dist: xlsxwriter (>=2.0.0,<3.0.0)
Project-URL: Repository, https://github.com/usds/justice40-tool
